gspread_helpers/__init__.py
gspread_helpers/range_name/__init__.py
gspread_helpers/range_name/exceptions.py
gspread_helpers/range_name/range_name.py
gspread_helpers/range_name/validations.py
gspread_helpers-0.0.24.dist-info/LICENSE
gspread_helpers-0.0.24.dist-info/METADATA
gspread_helpers-0.0.24.dist-info/WHEEL
gspread_helpers-0.0.24.dist-info/RECORD
